Metadata-Version: 2.1
Name: StringiPy
Version: 0.1.0
Summary: Python Functional String Utilities
Home-page: https://github.com/netxph/stringipy
Author: Marc Vitalis
Author-email: marc.vitalis@live.com
License: MIT
Platform: UNKNOWN
License-File: LICENSE
